{
  "posts": [
    {
      "id": 1,
      "title": "Getting Started with Java Programming",
      "excerpt": "A beginner's guide to Java programming covering fundamentals, OOP concepts, and best practices for new developers.",
      "content": "Java is one of the most popular programming languages in the world. In this blog, we'll explore the fundamentals of Java programming...",
      "image": "https://images.unsplash.com/photo-1517694712202-14dd9538aa97?w=600&h=400&fit=crop",
      "category": "Programming",
      "date": "2024-01-15",
      "readTime": "5 min",
      "author": "Anjani Kumar"
    },
    {
      "id": 2,
      "title": "Understanding Object-Oriented Programming",
      "excerpt": "Deep dive into OOP concepts: encapsulation, inheritance, polymorphism, and abstraction with practical examples.",
      "content": "Object-Oriented Programming (OOP) is a fundamental paradigm in software development. Let's understand its core concepts...",
      "image": "https://images.unsplash.com/photo-1555066931-4365d14bab8c?w=600&h=400&fit=crop",
      "category": "Concepts",
      "date": "2024-01-10",
      "readTime": "7 min",
      "author": "Anjani Kumar"
    },
    {
      "id": 3,
      "title": "Building Your First Python Project",
      "excerpt": "Step-by-step guide to creating your first Python project with practical examples and best practices.",
      "content": "Python is a versatile language perfect for beginners. In this guide, we'll build a complete project from scratch...",
      "image": "https://images.unsplash.com/photo-1526374965328-7f61d4dc18c5?w=600&h=400&fit=crop",
      "category": "Python",
      "date": "2024-01-05",
      "readTime": "6 min",
      "author": "Anjani Kumar"
    },
    {
      "id": 4,
      "title": "Introduction to Data Structures",
      "excerpt": "Learn the fundamentals of data structures and why they matter in programming.",
      "content": "Data structures are fundamental to programming. Understanding arrays, linked lists, stacks, and queues is essential...",
      "image": "https://images.unsplash.com/photo-1518770660439-4636190af475?w=600&h=400&fit=crop",
      "category": "DSA",
      "date": "2023-12-20",
      "readTime": "8 min",
      "author": "Anjani Kumar"
    },
    {
      "id": 5,
      "title": "Building Jarvis: My Virtual Assistant Project",
      "excerpt": "How I built a voice-controlled virtual assistant using Python and speech recognition.",
      "content": "Building a virtual assistant was an exciting project. In this blog, I'll share how I implemented voice recognition...",
      "image": "https://images.unsplash.com/photo-1485827404703-89b55fcc595e?w=600&h=400&fit=crop",
      "category": "AI",
      "date": "2023-12-10",
      "readTime": "10 min",
      "author": "Anjani Kumar"
    },
    {
      "id": 6,
      "title": "Tips for First Year CSE Students",
      "excerpt": "Advice and tips for students starting their journey in Computer Science Engineering.",
      "content": "Starting college can be overwhelming. Here are some tips that helped me succeed in my first year of CSE...",
      "image": "https://images.unsplash.com/photo-1523240795612-9a054b0db644?w=600&h=400&fit=crop",
      "category": "Education",
      "date": "2023-11-15",
      "readTime": "5 min",
      "author": "Anjani Kumar"
    }
  ]
}
